ampy/bars/v1/bars_pb2.py
ampy/common/v1/common_pb2.py
ampy/corporate_actions/v1/corporate_actions_pb2.py
ampy/fills/v1/fills_pb2.py
ampy/fundamentals/v1/fundamentals_pb2.py
ampy/fx/v1/fx_pb2.py
ampy/metrics/v1/metrics_pb2.py
ampy/news/v1/news_pb2.py
ampy/orders/v1/orders_pb2.py
ampy/positions/v1/positions_pb2.py
ampy/signals/v1/signals_pb2.py
ampy/ticks/v1/ticks_pb2.py
ampy/universe/v1/universe_pb2.py
ampy_proto-2.1.1.dist-info/licenses/LICENSE
ampy_proto-2.1.1.dist-info/METADATA
ampy_proto-2.1.1.dist-info/WHEEL
ampy_proto-2.1.1.dist-info/top_level.txt
ampy_proto-2.1.1.dist-info/RECORD
