Metadata-Version: 2.4
Name: ampy-proto
Version: 2.1.1
Summary: Canonical schemas for AmpyFin (generated Python protobufs)
Author: AmpyFin Team
License-Expression: MIT
Requires-Python: >=3.9
License-File: LICENSE
Requires-Dist: protobuf<7,>=6.32.0
Dynamic: license-file
